tcpgen/__init__.py
tcpgen/main.py
tcpgen-0.1.1.dist-info/LICENSE.txt
tcpgen-0.1.1.dist-info/METADATA
tcpgen-0.1.1.dist-info/WHEEL
tcpgen-0.1.1.dist-info/entry_points.txt
tcpgen-0.1.1.dist-info/top_level.txt
tcpgen-0.1.1.dist-info/RECORD
