Metadata-Version: 2.1
Name: tcpgen
Version: 0.1.1
Project-URL: Github, https://github.com/WillChamness/tcpgen
License-File: LICENSE.txt
